paternoster/__init__.py
paternoster/paternoster.py
paternoster/root.py
paternoster/shebang.py
paternoster/types.py
paternoster/runners/__init__.py
paternoster/runners/ansiblerunner.py
paternoster/types/__init__.py
paternoster-3.2.1.dist-info/DESCRIPTION.rst
paternoster-3.2.1.dist-info/METADATA
paternoster-3.2.1.dist-info/RECORD
paternoster-3.2.1.dist-info/WHEEL
paternoster-3.2.1.dist-info/entry_points.txt
paternoster-3.2.1.dist-info/metadata.json
paternoster-3.2.1.dist-info/top_level.txt
paternoster-3.2.1.dist-info/zip-safe
